Allo/__init__.py
Allo/allo
Allo/allocation.py
Allo/atac.json
Allo/atac.weights.h5
Allo/dnase.json
Allo/dnase.weights.h5
Allo/mixed.json
Allo/mixed.weights.h5
Allo/narrow.json
Allo/narrow.weights.h5
Allo/predictPeak.py
bio_allo-1.2.0.data/scripts/allo
bio_allo-1.2.0.dist-info/LICENSE.txt
bio_allo-1.2.0.dist-info/METADATA
bio_allo-1.2.0.dist-info/WHEEL
bio_allo-1.2.0.dist-info/top_level.txt
bio_allo-1.2.0.dist-info/RECORD
